git_secret_protector/__init__.py
git_secret_protector/context/__init__.py
git_secret_protector/context/module.py
git_secret_protector/core/__init__.py
git_secret_protector/core/git_attributes_parser.py
git_secret_protector/core/settings.py
git_secret_protector/crypto/__init__.py
git_secret_protector/crypto/aes_encryption_handler.py
git_secret_protector/crypto/aes_key_manager.py
git_secret_protector/error/aes_key_error.py
git_secret_protector/error/storage_error.py
git_secret_protector/main.py
git_secret_protector/services/__init__.py
git_secret_protector/services/encryption_manager.py
git_secret_protector/services/key_rotator.py
git_secret_protector/storage/__init__.py
git_secret_protector/storage/aws_ssm_storage_manager.py
git_secret_protector/storage/gcp_secret_storage_manager.py
git_secret_protector/storage/storage_manager_factory.py
git_secret_protector/storage/storage_manager_interface.py
git_secret_protector/utils/__init__.py
git_secret_protector/utils/configure_logging.py
git_secret_protector/utils/project_version.py
git_secret_protector-1.2.4.dist-info/METADATA
git_secret_protector-1.2.4.dist-info/WHEEL
git_secret_protector-1.2.4.dist-info/entry_points.txt
git_secret_protector-1.2.4.dist-info/RECORD
