Metadata-Version: 2.3
Name: git-secret-protector
Version: 1.2.4
Summary: A tool for managing secrets in Git with AWS Parameter Store integration.
Author: Duc Duong
Author-email: duc.duong@c0x12c.com
Requires-Python: >=3.10,<3.14
Classifier: Programming Language :: Python :: 3
Classifier: Programming Language :: Python :: 3.10
Classifier: Programming Language :: Python :: 3.11
Classifier: Programming Language :: Python :: 3.12
Classifier: Programming Language :: Python :: 3.13
Requires-Dist: boto3 (>=1.35.44,<2.0.0)
Requires-Dist: google-auth (>=2.36.0,<3.0.0)
Requires-Dist: google-cloud-secret-manager (>=2.20.2,<3.0.0)
Requires-Dist: injector (>=0.22.0,<0.23.0)
Requires-Dist: pycryptodome (>=3.20.0,<4.0.0)
